libru/__init__.py
libru/cli.py
libru/libru.py
libru-0.1.3.dist-info/entry_points.txt
libru-0.1.3.dist-info/LICENSE
libru-0.1.3.dist-info/WHEEL
libru-0.1.3.dist-info/METADATA
libru-0.1.3.dist-info/RECORD
